{"stats":{"minecraft:killed_by":{"crittersandcompanions:otter":1,"minecraft:player":5,"darkestsouls:gravetender_hollow_longsword":1},"minecraft:picked_up":{"minecraft:wooden_axe":3,"minecraft:iron_chestplate":1,"minecraft:wheat":1,"minecraft:chainmail_boots":1,"darkestsouls:beast_blood_clump":4,"minecraft:soul_soil":2,"minecraft:raw_copper":119,"minecraft:cobbled_deepslate":208,"minecraft:spruce_planks":8,"minecraft:iron_pickaxe":2,"minecraft:melon_slice":18,"minecraft:coal_block":2,"irons_spellbooks:inscription_table":2,"minecraft:furnace":8,"minecraft:stick":13,"minecraft:torch":4,"minecraft:acacia_log":6,"minecraft:porkchop":59,"minecraft:diorite":46,"minecraft:orange_bed":3,"minecraft:rotten_flesh":2,"crittersandcompanions:dragonfly_wing":1,"farmersdelight:onion":43,"minecraft:iron_block":149,"born_in_chaos_v1:bonescaller_staff":1,"alexsmobs:emu_egg":1,"supplementaries:ash":1,"irons_spellbooks:arcane_debris":2,"minecraft:stripped_birch_wood":1,"alexsmobs:mungal_spores":1,"minecraft:cobblestone":997,"minecraft:birch_log":18,"minecraft:pink_petals":53,"minecraft:feather":7,"born_in_chaos_v1:spiritual_dust":2,"minecraft:birch_slab":1,"minecraft:andesite":5,"minecraft:jungle_log":2,"immersive_aircraft:warship":1,"minecraft:potato":27,"minecraft:flint":5,"minecraft:lapis_lazuli":8,"minecraft:dirt":1274,"minecraft:lantern":1,"born_in_chaos_v1:monster_skin":2,"born_in_chaos_v1:marigolds":1,"minecraft:bone":67,"minecraft:acacia_planks":4,"minecraft:stonecutter":1,"minecraft:bow":1,"minecraft:wheat_seeds":21,"minecraft:mossy_stone_bricks":1,"minecraft:fletching_table":3,"minecraft:bamboo":1,"minecraft:oak_planks":16,"minecraft:cooked_porkchop":10,"minecraft:sand":12,"minecraft:stripped_spruce_log":3,"minecraft:cyan_bed":2,"minecraft:mossy_cobblestone":8,"minecraft:spruce_boat":3,"waystones:waystone":8,"minecraft:granite":13,"minecraft:emerald":3,"minecraft:andesite_slab":2,"minecraft:cocoa_beans":3,"minecraft:crafting_table":16,"minecraft:allium":42,"minecraft:chicken":2,"minecraft:brown_mushroom":27,"gravestone:obituary":18,"minecraft:shield":1,"minecraft:red_bed":2,"minecraft:iron_axe":1,"minecraft:flint_and_steel":1,"tacz:ammo":100,"minecraft:iron_shovel":1,"minecraft:beef":23,"minecraft:oak_boat":10,"born_in_chaos_v1:gnawed_bones":1,"minecraft:jungle_sapling":1,"minecraft:spruce_slab":1,"minecraft:lectern":2,"minecraft:sugar_cane":12,"minecraft:chest":10,"minecraft:spruce_trapdoor":1,"minecraft:egg":4,"minecraft:raw_iron":1,"automobility:automobile_assembler":1,"born_in_chaos_v1:pieceofdarkmetal":14,"minecraft:carrot":53,"minecraft:light_blue_bed":2,"minecraft:dark_oak_planks":1,"minecraft:stone_shovel":1,"minecraft:hay_block":46,"minecraft:saddle":1,"minecraft:mutton":18,"minecraft:white_wool":15,"born_in_chaos_v1:monster_flesh":2,"minecraft:salmon":6,"minecraft:leather":10,"minecraft:acacia_wood":3,"minecraft:filled_map":1,"minecraft:birch_planks":90,"minecraft:oak_log":23,"minecraft:golden_boots":1,"minecraft:cooked_mutton":5,"minecraft:kelp":43,"automobility:auto_mechanic_table":6,"mowziesmobs:foliaath_seed":1,"minecraft:rabbit_hide":3,"minecraft:iron_ingot":82,"minecraft:stone_pickaxe":3,"minecraft:flowering_azalea":3,"minecraft:sweet_berries":17,"born_in_chaos_v1:ethereal_spirit":2,"minecraft:gravel":31,"born_in_chaos_v1:dark_rod":1,"minecraft:amethyst_shard":17,"minecraft:blast_furnace":3,"minecraft:spruce_sapling":1,"minecraft:white_bed":11,"minecraft:spruce_log":4,"darkestsouls:siderite_fragment":18,"minecraft:stone_axe":1,"tacz:modern_kinetic_gun":6,"minecraft:chainmail_leggings":1,"minecraft:iron_helmet":2,"minecraft:gray_wool":1,"darkestsouls:small_soul_fragment":13,"minecraft:baked_potato":13,"minecraft:melon_seeds":1,"minecraft:stripped_dark_oak_log":11,"minecraft:coal":115},"minecraft:mined":{"minecraft:dark_oak_planks":1,"minecraft:spruce_planks":3,"minecraft:white_bed":9,"minecraft:jungle_leaves":4,"minecraft:obsidian":1,"minecraft:spruce_trapdoor":1,"minecraft:granite":13,"minecraft:acacia_log":6,"minecraft:grass_block":108,"minecraft:jungle_log":2,"darkestsouls:deepslate_siderite_ore":10,"minecraft:coal_block":2,"automobility:auto_mechanic_table":5,"minecraft:light_blue_stained_glass":2,"automobility:automobile_assembler":1,"minecraft:cobbled_deepslate":3,"minecraft:iron_ore":1,"minecraft:fire":2,"minecraft:deepslate_lapis_ore":1,"minecraft:fletching_table":3,"supplementaries:stick":1,"minecraft:iron_block":150,"minecraft:spruce_slab":1,"minecraft:orange_bed":3,"minecraft:brown_mushroom":1,"minecraft:red_bed":2,"minecraft:kelp_plant":9,"minecraft:powder_snow":26,"minecraft:blast_furnace":2,"minecraft:melon":3,"minecraft:chest":18,"minecraft:mushroom_stem":1,"minecraft:cobblestone":60,"minecraft:cyan_bed":1,"minecraft:oak_planks":16,"minecraft:wall_torch":3,"minecraft:pink_petals":31,"minecraft:birch_log":17,"minecraft:wheat":1,"minecraft:grass":152,"minecraft:oak_log":23,"minecraft:sand":10,"minecraft:dirt":143,"minecraft:stripped_birch_wood":1,"minecraft:stonecutter":1,"minecraft:oak_leaves":22,"minecraft:deepslate":321,"farmersdelight:onions":2,"minecraft:mossy_cobblestone":6,"farmersdelight:wild_carrots":22,"gravestone:gravestone":21,"minecraft:allium":3,"minecraft:brown_mushroom_block":2,"minecraft:polished_andesite_slab":4,"minecraft:birch_slab":1,"minecraft:spruce_leaves":8,"minecraft:hay_block":47,"farmersdelight:wild_onions":21,"minecraft:furnace":7,"minecraft:carrots":5,"minecraft:acacia_wood":3,"minecraft:andesite":8,"minecraft:stripped_spruce_log":4,"minecraft:potatoes":4,"minecraft:vine":1,"minecraft:bamboo":1,"irons_spellbooks:inscription_table":2,"minecraft:stone":929,"minecraft:white_wool":2,"minecraft:glass_pane":1,"born_in_chaos_v1:marigolds":1,"minecraft:stripped_dark_oak_log":11,"minecraft:crafting_table":16,"minecraft:emerald_ore":3,"morevillagers:oceanography_table":1,"minecraft:andesite_slab":4,"minecraft:lectern":1,"minecraft:copper_ore":34,"minecraft:tall_grass":13,"minecraft:diorite":47,"minecraft:blue_bed":1,"minecraft:birch_planks":3,"minecraft:light_blue_bed":2,"minecraft:sweet_berry_bush":7,"minecraft:spruce_log":4,"minecraft:birch_leaves":27,"minecraft:coal_ore":72,"darkestsouls:cinnabar_ore":2,"minecraft:mycelium":1035,"minecraft:gravel":36,"minecraft:fern":1},"minecraft:killed":{"darkestsouls:ashen_blood_beast_patient":1,"born_in_chaos_v1:baby_skeleton_minion":1,"minecraft:skeleton":1,"minecraft:chicken":2,"darkestsouls:beast_patient":2,"darkestsouls:hollow_assassin":2,"minecraft:pig":22,"minecraft:salmon":6,"minecraft:sheep":10,"minecraft:pillager":1,"minecraft:zombie":1,"born_in_chaos_v1:dread_hound":2,"alexsmobs:mungus":1,"born_in_chaos_v1:door_knight":1,"minecraft:cow":8,"alexsmobs:tasmanian_devil":1,"born_in_chaos_v1:thornshell_crab":1,"enemyexpansion:direwolf":1,"alexsmobs:sugar_glider":1,"born_in_chaos_v1:zombie_bruiser":1,"darkestsouls:hollow_broken_straightsword":5,"born_in_chaos_v1:baby_skeleton":1,"born_in_chaos_v1:decrepit_skeleton":1,"born_in_chaos_v1:nightmare_stalker":1},"minecraft:broken":{"minecraft:iron_shovel":2,"minecraft:stone_pickaxe":1,"minecraft:stone_shovel":4,"minecraft:flint_and_steel":1,"minecraft:iron_pickaxe":1},"minecraft:dropped":{"minecraft:lapis_lazuli":8,"minecraft:baked_potato":3,"minecraft:crafting_table":1,"minecraft:cooked_porkchop":3,"minecraft:leather":7,"born_in_chaos_v1:pieceofdarkmetal":14,"minecraft:flint":3,"born_in_chaos_v1:monster_flesh":2,"minecraft:dirt":48,"born_in_chaos_v1:monster_skin":2,"farmersdelight:onion":18,"minecraft:jungle_sapling":1,"gravestone:obituary":45,"minecraft:wooden_sword":3,"minecraft:sand":11,"minecraft:iron_pickaxe":1,"minecraft:white_wool":2,"minecraft:bone":2,"minecraft:stone_axe":2,"alexsmobs:animal_dictionary":1,"minecraft:cobbled_deepslate":64,"minecraft:wheat":1,"born_in_chaos_v1:ethereal_spirit":2,"minecraft:rotten_flesh":1,"minecraft:oak_planks":2,"minecraft:golden_shovel":1,"minecraft:carrot":11,"minecraft:rabbit_hide":3,"irons_spellbooks:arcane_debris":1,"minecraft:chainmail_boots":1,"minecraft:lectern":1,"minecraft:iron_ingot":32,"minecraft:golden_boots":1,"minecraft:wheat_seeds":14,"minecraft:mossy_cobblestone":2,"darkestsouls:small_soul_fragment":3,"minecraft:iron_helmet":1,"minecraft:feather":3,"minecraft:cobblestone":68,"minecraft:granite":13,"crittersandcompanions:dragonfly_wing":1,"minecraft:stick":11,"born_in_chaos_v1:gnawed_bones":1,"minecraft:diorite":24,"minecraft:wooden_axe":4,"minecraft:melon_slice":2,"tacz:modern_kinetic_gun":3,"minecraft:flowering_azalea":3,"minecraft:stonecutter":1,"minecraft:iron_axe":2,"minecraft:iron_shovel":1,"minecraft:chainmail_leggings":1,"minecraft:pink_petals":25,"minecraft:acacia_planks":4,"darkestsouls:siderite_fragment":9,"minecraft:spruce_sapling":1,"minecraft:soul_soil":2,"minecraft:cocoa_beans":3,"minecraft:stone_shovel":1,"born_in_chaos_v1:spiritual_dust":2,"minecraft:filled_map":1,"minecraft:potato":15,"minecraft:allium":42,"minecraft:spruce_trapdoor":1,"minecraft:spruce_planks":2,"minecraft:iron_chestplate":1,"minecraft:andesite":1,"minecraft:oak_boat":2,"minecraft:stone_pickaxe":5,"minecraft:wooden_pickaxe":1,"waystones:waystone":1,"minecraft:cyan_bed":1},"minecraft:used":{"minecraft:iron_shovel":559,"born_in_chaos_v1:bonescaller_staff":10,"minecraft:spruce_slab":1,"minecraft:chest":19,"minecraft:shield":16,"minecraft:stone":18,"minecraft:rotten_flesh":1,"minecraft:iron_chestplate":3,"minecraft:mutton":9,"minecraft:carrot":38,"minecraft:spruce_boat":3,"minecraft:lantern":1,"minecraft:iron_helmet":2,"minecraft:light_blue_bed":2,"minecraft:sweet_berries":3,"minecraft:furnace":15,"minecraft:egg":4,"minecraft:potato":15,"minecraft:mossy_stone_bricks":1,"minecraft:diorite":9,"minecraft:stone_pickaxe":305,"minecraft:oak_planks":18,"minecraft:wooden_pickaxe":47,"minecraft:leather_chestplate":1,"minecraft:white_wool":1,"minecraft:golden_apple":4,"minecraft:sand":1,"minecraft:blast_furnace":2,"waystones:waystone":6,"automobility:auto_mechanic_table":5,"minecraft:birch_slab":3,"minecraft:melon_slice":14,"minecraft:bread":18,"born_in_chaos_v1:marigolds":1,"minecraft:wooden_sword":24,"minecraft:chainmail_boots":1,"minecraft:birch_log":2,"minecraft:andesite":1,"minecraft:oak_boat":7,"legendary_monsters:fiery_jaw":1,"minecraft:stone_sword":4,"minecraft:flint_and_steel":64,"minecraft:stone_shovel":539,"minecraft:spruce_planks":4,"immersive_aircraft:warship":1,"minecraft:orange_bed":3,"minecraft:stick":3,"minecraft:torch":43,"minecraft:dirt":229,"minecraft:chainmail_chestplate":1,"minecraft:dark_oak_planks":3,"minecraft:wooden_axe":61,"minecraft:iron_axe":66,"irons_spellbooks:arcane_debris":1,"minecraft:iron_boots":3,"minecraft:golden_carrot":3,"minecraft:beef":13,"minecraft:cobbled_deepslate":102,"minecraft:iron_leggings":2,"minecraft:water_bucket":1,"minecraft:birch_planks":3,"minecraft:baked_potato":10,"minecraft:salmon":6,"minecraft:mossy_cobblestone":6,"farmersdelight:onion":24,"minecraft:crafting_table":33,"minecraft:red_bed":2,"minecraft:white_bed":11,"minecraft:oak_log":1,"minecraft:diamond_pickaxe":966,"minecraft:chicken":1,"minecraft:iron_pickaxe":389,"minecraft:leather_helmet":1,"minecraft:stone_axe":62,"minecraft:pink_petals":5,"minecraft:cobblestone":344,"minecraft:cooked_porkchop":17,"minecraft:porkchop":19,"minecraft:bucket":1,"minecraft:chainmail_leggings":1,"irons_spellbooks:inscription_table":2},"minecraft:crafted":{"minecraft:oak_planks":124,"minecraft:birch_slab":6,"minecraft:stone":32,"minecraft:iron_boots":2,"minecraft:chest":9,"minecraft:cooked_porkchop":19,"minecraft:crafting_table":18,"minecraft:spruce_planks":28,"minecraft:wooden_pickaxe":5,"minecraft:birch_planks":52,"minecraft:iron_chestplate":1,"minecraft:paper":3,"minecraft:diamond_pickaxe":1,"minecraft:shield":1,"minecraft:stick":112,"minecraft:iron_ingot":63,"minecraft:iron_pickaxe":1,"minecraft:stone_sword":1,"minecraft:wooden_sword":4,"minecraft:stone_shovel":4,"minecraft:furnace":7,"minecraft:iron_axe":1,"minecraft:stone_pickaxe":6,"minecraft:spruce_boat":2,"minecraft:dark_oak_planks":44,"minecraft:cooked_beef":4,"minecraft:stone_axe":2,"minecraft:oak_boat":1,"minecraft:wooden_axe":4,"minecraft:iron_shovel":4,"minecraft:iron_leggings":1,"minecraft:white_bed":3,"minecraft:acacia_planks":20,"minecraft:torch":40},"minecraft:custom":{"minecraft:interact_with_crafting_table":73,"minecraft:open_barrel":22,"minecraft:leave_game":12,"minecraft:time_since_death":164710,"minecraft:sprint_one_cm":1457052,"minecraft:damage_blocked_by_shield":705,"minecraft:drop":311,"minecraft:talked_to_villager":5,"minecraft:play_time":911979,"minecraft:deaths":32,"minecraft:jump":14125,"minecraft:walk_on_water_one_cm":304378,"minecraft:interact_with_furnace":32,"minecraft:sleep_in_bed":39,"minecraft:waystone_activated":7,"minecraft:damage_dealt":7400,"minecraft:player_kills":1,"minecraft:crouch_one_cm":94710,"minecraft:mob_kills":79,"minecraft:damage_dealt_resisted":1175,"minecraft:climb_one_cm":18357,"minecraft:walk_one_cm":1676064,"minecraft:sneak_time":46252,"minecraft:walk_under_water_one_cm":130165,"minecraft:boat_one_cm":929504,"minecraft:interact_with_lectern":3,"minecraft:interact_with_blast_furnace":4,"minecraft:total_world_time":911979,"minecraft:time_since_rest":44882,"minecraft:damage_taken":12979,"minecraft:damage_absorbed":50,"minecraft:swim_one_cm":212423,"minecraft:fly_one_cm":1896918,"minecraft:open_chest":190,"minecraft:fall_one_cm":316069}},"DataVersion":3465}